abrade/__init__.py
abrade/base.py
abrade/exceptions.py
abrade-0.1.1.dist-info/LICENSE
abrade-0.1.1.dist-info/METADATA
abrade-0.1.1.dist-info/WHEEL
abrade-0.1.1.dist-info/top_level.txt
abrade-0.1.1.dist-info/RECORD
