Metadata-Version: 2.1
Name: abrade
Version: 0.1.1
Summary: A simple, generic web scraper and parser
Home-page: https://github.com/DMNh/abrade
Author: Dan Lewis
Author-email: D@nLew.is
License: UNKNOWN
Platform: UNKNOWN
Classifier: Programming Language :: Python :: 3
Classifier: License :: OSI Approved :: MIT License
Classifier: Operating System :: OS Independent
Requires-Python: >=3.6
Requires-Dist: requests
Requires-Dist: bs4
